LICENSE
MANIFEST.in
README.md
pyproject.toml
setup.cfg
app1/__init__.py
app1/admin.py
app1/apps.py
app1/models.py
app1/tests.py
app1/urls.py
app1/views.py
app1/migrations/0001_initial.py
app1/migrations/__init__.py
app1/static/app1/css/style.css
app1/static/app1/images/bg.jpg
app1/templates/admin/base_site.html
app1/templates/admin/index.html
app1/templates/app1/detail.html
app1/templates/app1/index.html
app1/templates/app1/results.html
django_poll_devin.egg-info/PKG-INFO
django_poll_devin.egg-info/SOURCES.txt
django_poll_devin.egg-info/dependency_links.txt
django_poll_devin.egg-info/requires.txt
django_poll_devin.egg-info/top_level.txt