Metadata-Version: 2.1
Name: django-poll-devin
Version: 0.1
Summary: A Django app to conduct web-based polls.
Home-page: https://devin.com/
Author: Devin
Author-email: stemm@foxmail.com
License: MIT License  # Example license
Platform: UNKNOWN
Classifier: Environment :: Web Environment
Classifier: Framework :: Django
Classifier: Intended Audience :: Developers
Classifier: License :: OSI Approved :: MIT License
Classifier: Operating System :: OS Independent
Classifier: Programming Language :: Python :: 3
Classifier: Topic :: Internet :: WWW/HTTP
Classifier: Topic :: Internet :: WWW/HTTP :: Dynamic Content
Requires-Python: >=3.0
License-File: LICENSE
